rigorous_recorder/__init__.py
rigorous_recorder/settings.json
rigorous_recorder/__dependencies__/__init__.py
rigorous_recorder/__dependencies__/__sources__/.keep
rigorous_recorder/__dependencies__/__sources__/file_system_py/.gitignore
rigorous_recorder/__dependencies__/__sources__/file_system_py/.gitrepo
rigorous_recorder/__dependencies__/__sources__/file_system_py/README.md
rigorous_recorder/__dependencies__/__sources__/file_system_py/poetry.lock
rigorous_recorder/__dependencies__/__sources__/file_system_py/pyproject.toml
rigorous_recorder/__dependencies__/__sources__/file_system_py/commands/pip
rigorous_recorder/__dependencies__/__sources__/file_system_py/commands/shell
rigorous_recorder/__dependencies__/__sources__/file_system_py/commands/start
rigorous_recorder/__dependencies__/__sources__/file_system_py/commands/subrepo
rigorous_recorder/__dependencies__/__sources__/file_system_py/commands/project/clean
rigorous_recorder/__dependencies__/__sources__/file_system_py/commands/project/commands
rigorous_recorder/__dependencies__/__sources__/file_system_py/commands/project/local_install
rigorous_recorder/__dependencies__/__sources__/file_system_py/commands/project/publish
rigorous_recorder/__dependencies__/__sources__/file_system_py/commands/project/purge
rigorous_recorder/__dependencies__/__sources__/file_system_py/documentation/fornix_framework.md
rigorous_recorder/__dependencies__/__sources__/file_system_py/documentation/setup.md
rigorous_recorder/__dependencies__/__sources__/file_system_py/documentation/images/cd_tutorial.gif
rigorous_recorder/__dependencies__/__sources__/file_system_py/documentation/images/package_from_example.png
rigorous_recorder/__dependencies__/__sources__/file_system_py/documentation/images/package_name.png
rigorous_recorder/__dependencies__/__sources__/file_system_py/documentation/images/package_versions.png
rigorous_recorder/__dependencies__/__sources__/file_system_py/logs/main.py.log
rigorous_recorder-1.4.4.dist-info/METADATA
rigorous_recorder-1.4.4.dist-info/WHEEL
rigorous_recorder-1.4.4.dist-info/top_level.txt
rigorous_recorder-1.4.4.dist-info/RECORD
