Metadata-Version: 2.1
Name: rigorous-recorder
Version: 1.4.4
Summary: Save everything in a filterable way
Home-page: https://github.com/jeff-hykin/rigorous_recorder.git
Author: Jeff Hykin
Author-email: jeff.hykin@gmail.com
License: MIT
Platform: UNKNOWN
Classifier: Intended Audience :: Developers
Classifier: Programming Language :: Python
Classifier: Programming Language :: Python :: 3
Classifier: Operating System :: OS Independent
Requires-Python: >=3.6
